arrangelt/__init__.py
arrangelt/core.py
arrangelt/utils.py
arrangelt/tests/__init__.py
arrangelt/tests/test_core.py
arrangelt-0.3.2.dist-info/licenses/LICENSE
arrangelt-0.3.2.dist-info/METADATA
arrangelt-0.3.2.dist-info/WHEEL
arrangelt-0.3.2.dist-info/top_level.txt
arrangelt-0.3.2.dist-info/RECORD
