Metadata-Version: 2.4
Name: arrangelt
Version: 0.3.2
Summary: A Python library for sorting and organizing files into usable lists or dictionaries.
Home-page: https://github.com/NullAce/arrangelt
Author: Austin Pratt
Author-email: 183548723+NullAce@users.noreply.github.com
License: Apache License 2.0
Classifier: Programming Language :: Python :: 3
Classifier: License :: OSI Approved :: Apache Software License
Classifier: Operating System :: OS Independent
Requires-Python: >=3.6
License-File: LICENSE
Dynamic: author
Dynamic: author-email
Dynamic: classifier
Dynamic: description
Dynamic: description-content-type
Dynamic: home-page
Dynamic: license
Dynamic: license-file
Dynamic: requires-python
Dynamic: summary
